colorOS/Align.py
colorOS/Background.py
colorOS/Color.py
colorOS/Location.py
colorOS/Reset.py
colorOS/Screen.py
colorOS/Terminal.py
colorOS/Text.py
colorOS/__init__.py
coloros-0.2.dist-info/METADATA
coloros-0.2.dist-info/WHEEL
coloros-0.2.dist-info/top_level.txt
coloros-0.2.dist-info/RECORD
