Metadata-Version: 2.4
Name: colorOS
Version: 0.2
Summary: Terminal renk ve konumlandırma kütüphanesi
Home-page: https://github.com/TheRaven
Author: TheRaven
Author-email: RavenisThere@proton.me
Classifier: Programming Language :: Python :: 3
Classifier: Operating System :: OS Independent
Classifier: License :: OSI Approved :: MIT License
Requires-Python: >=3.7
Dynamic: author
Dynamic: author-email
Dynamic: classifier
Dynamic: description
Dynamic: description-content-type
Dynamic: home-page
Dynamic: requires-python
Dynamic: summary
